lsyflasksdkcore/__init__.py
lsyflasksdkcore/blueprints.py
lsyflasksdkcore/context.py
lsyflasksdkcore/excel.py
lsyflasksdkcore/exceptions.py
lsyflasksdkcore/model.py
lsyflasksdkcore/sae.py
lsyflasksdkcore/schema.py
lsyflasksdkcore/serialization.py
lsyflasksdkcore/sqlalchemy_factory.py
lsyflasksdkcore/decorators/__init__.py
lsyflasksdkcore/export/__init__.py
lsyflasksdkcore/export/csv.py
lsyflasksdkcore/export/xls.py
lsyflasksdkcore/linq/__init__.py
lsyflasksdkcore/linq/core.py
lsyflasksdkcore/linq/linq_exceptions.py
lsyflasksdkcore/logging/__init__.py
lsyflasksdkcore/logging/file_logger.py
lsyflasksdkcore/logging/stash_logger.py
lsyflasksdkcore/swagger/__init__.py
lsyflasksdkcore/swagger/doc.py
lsyflasksdkcore/swagger/plugins.py
lsyflasksdkcore/swagger/test.py
lsyflasksdkcore/utils/__init__.py
lsyflasksdkcore/utils/lazy.py
lsyflasksdkcore/utils/singleton_meta.py
lsyflasksdkcore/utils/sm2encry.py
lsyflasksdkcore/utils/sm2utils.py
lsyflasksdkcore/utils/token_utils.py
lsyflasksdkcore/utils/tree.py
lsyflasksdkcore/utils/unique.py
lsyflasksdkcore_v0-1.0.1.dist-info/licenses/LICENSE
lsyflasksdkcore_v0-1.0.1.dist-info/METADATA
lsyflasksdkcore_v0-1.0.1.dist-info/WHEEL
lsyflasksdkcore_v0-1.0.1.dist-info/top_level.txt
lsyflasksdkcore_v0-1.0.1.dist-info/RECORD
