Metadata-Version: 2.4
Name: lsyflasksdkcore_v0
Version: 1.0.1
Summary: 领数云flask SDK核心库（https://github.com/9kl/lsyflasksdkcore）
Home-page: https://github.com/9kl/lsyflasksdkcore
Author: fhp
Author-email: chinafengheping@outlook.com
License:                                  Apache License
Classifier: Programming Language :: Python :: 3
Classifier: License :: OSI Approved :: Apache Software License
Classifier: Operating System :: OS Independent
Requires-Python: >=3.8
License-File: LICENSE
Requires-Dist: apispec==4.4.0
Requires-Dist: apispec-webframeworks==0.5.2
Requires-Dist: blinker==1.9.0
Requires-Dist: click==8.3.0
Requires-Dist: colorama==0.4.6
Requires-Dist: Flask==3.0.3
Requires-Dist: Flask-Login==0.6.3
Requires-Dist: Flask-SQLAlchemy==3.1.1
Requires-Dist: GeoAlchemy2==0.14.7
Requires-Dist: gmssl==3.2.1
Requires-Dist: greenlet==3.2.4
Requires-Dist: itsdangerous==2.2.0
Requires-Dist: Jinja2==3.1.6
Requires-Dist: MarkupSafe==3.0.2
Requires-Dist: marshmallow==3.11.1
Requires-Dist: packaging==25.0
Requires-Dist: PyJWT==2.1.0
Requires-Dist: python-logstash==0.4.8
Requires-Dist: PyYAML==6.0.2
Requires-Dist: six==1.16.0
Requires-Dist: SQLAlchemy==2.0.43
Requires-Dist: swagger-ui-py==0.3.0
Requires-Dist: typing_extensions==4.15.0
Requires-Dist: Werkzeug==3.1.3
Requires-Dist: xlrd==1.2.0
Requires-Dist: xlutils==2.0.0
Requires-Dist: xlwt==1.3.0
Dynamic: author
Dynamic: author-email
Dynamic: classifier
Dynamic: description
Dynamic: description-content-type
Dynamic: home-page
Dynamic: license
Dynamic: license-file
Dynamic: requires-dist
Dynamic: requires-python
Dynamic: summary
